{
    "sourceFile": "package.json",
    "activeCommit": 0,
    "commits": [
        {
            "activePatchIndex": 1,
            "patches": [
                {
                    "date": 1651506984928,
                    "content": "Index: \n===================================================================\n--- \n+++ \n"
                },
                {
                    "date": 1652636323186,
                    "content": "Index: \n===================================================================\n--- \n+++ \n@@ -1,57 +1,65 @@\n-{\n-  \"name\": \"app2\",\n-  \"version\": \"0.0.1\",\n-  \"private\": true,\n-  \"scripts\": {\n-    \"android\": \"react-native run-android\",\n-    \"ios\": \"react-native run-ios\",\n-    \"start\": \"react-native start\",\n-    \"test\": \"jest\",\n-    \"lint\": \"eslint . --ext .js,.jsx,.ts,.tsx\"\n-  },\n-  \"dependencies\": {\n-    \"@react-navigation/bottom-tabs\": \"^6.3.1\",\n-    \"@react-navigation/material-top-tabs\": \"^6.2.1\",\n-    \"@react-navigation/native\": \"^6.0.10\",\n-    \"@react-navigation/native-stack\": \"^6.6.1\",\n-    \"react\": \"17.0.2\",\n-    \"react-native\": \"0.68.0\",\n-    \"react-native-pager-view\": \"^5.4.15\",\n-    \"react-native-responsive-fontsize\": \"^0.5.1\",\n-    \"react-native-safe-area-context\": \"^4.2.4\",\n-    \"react-native-screens\": \"^3.13.1\",\n-    \"react-native-tab-view\": \"^3.1.1\",\n-    \"react-navigation-tabs\": \"^2.11.2\"\n-  },\n-  \"devDependencies\": {\n-    \"@babel/core\": \"^7.12.9\",\n-    \"@babel/runtime\": \"^7.12.5\",\n-    \"@react-native-community/eslint-config\": \"^2.0.0\",\n-    \"@types/jest\": \"^27.4.1\",\n-    \"@types/react\": \"^18.0.3\",\n-    \"@types/react-native\": \"^0.67.4\",\n-    \"@types/react-test-renderer\": \"^18.0.0\",\n-    \"@typescript-eslint/eslint-plugin\": \"^5.17.0\",\n-    \"@typescript-eslint/parser\": \"^5.17.0\",\n-    \"babel-jest\": \"^26.6.3\",\n-    \"eslint\": \"^7.32.0\",\n-    \"jest\": \"^26.6.3\",\n-    \"metro-react-native-babel-preset\": \"^0.67.0\",\n-    \"react-test-renderer\": \"17.0.2\",\n-    \"typescript\": \"^4.6.3\"\n-  },\n-  \"resolutions\": {\n-    \"@types/react\": \"^17\"\n-  },\n-  \"jest\": {\n-    \"preset\": \"react-native\",\n-    \"moduleFileExtensions\": [\n-      \"ts\",\n-      \"tsx\",\n-      \"js\",\n-      \"jsx\",\n-      \"json\",\n-      \"node\"\n-    ]\n-  }\n-}\n+{\r\n+  \"name\": \"app2\",\r\n+  \"version\": \"0.0.1\",\r\n+  \"private\": true,\r\n+  \"scripts\": {\r\n+    \"android\": \"react-native run-android\",\r\n+    \"ios\": \"react-native run-ios\",\r\n+    \"start\": \"react-native start\",\r\n+    \"test\": \"jest\",\r\n+    \"lint\": \"eslint . --ext .js,.jsx,.ts,.tsx\"\r\n+  },\r\n+  \"dependencies\": {\r\n+    \"@react-native-community/async-storage\": \"^1.12.1\",\r\n+    \"@react-navigation/bottom-tabs\": \"^6.3.1\",\r\n+    \"@react-navigation/material-top-tabs\": \"^6.2.1\",\r\n+    \"@react-navigation/native\": \"^6.0.10\",\r\n+    \"@react-navigation/native-stack\": \"^6.6.1\",\r\n+    \"axios\": \"^0.27.2\",\r\n+    \"react\": \"17.0.2\",\r\n+    \"react-native\": \"0.68.0\",\r\n+    \"react-native-axios\": \"^0.17.1\",\r\n+    \"react-native-pager-view\": \"^5.4.15\",\r\n+    \"react-native-responsive-fontsize\": \"^0.5.1\",\r\n+    \"react-native-safe-area-context\": \"^4.2.4\",\r\n+    \"react-native-screens\": \"^3.13.1\",\r\n+    \"react-native-tab-view\": \"^3.1.1\",\r\n+    \"react-navigation-tabs\": \"^2.11.2\",\r\n+    \"react-redux\": \"^8.0.1\",\r\n+    \"realm\": \"^10.17.0\",\r\n+    \"redux\": \"^4.2.0\",\r\n+    \"redux-persist\": \"^6.0.0\",\r\n+    \"redux-saga\": \"^1.1.3\"\r\n+  },\r\n+  \"devDependencies\": {\r\n+    \"@babel/core\": \"^7.12.9\",\r\n+    \"@babel/runtime\": \"^7.12.5\",\r\n+    \"@react-native-community/eslint-config\": \"^2.0.0\",\r\n+    \"@types/jest\": \"^27.4.1\",\r\n+    \"@types/react\": \"^18.0.3\",\r\n+    \"@types/react-native\": \"^0.67.4\",\r\n+    \"@types/react-test-renderer\": \"^18.0.0\",\r\n+    \"@typescript-eslint/eslint-plugin\": \"^5.17.0\",\r\n+    \"@typescript-eslint/parser\": \"^5.17.0\",\r\n+    \"babel-jest\": \"^26.6.3\",\r\n+    \"eslint\": \"^7.32.0\",\r\n+    \"jest\": \"^26.6.3\",\r\n+    \"metro-react-native-babel-preset\": \"^0.67.0\",\r\n+    \"react-test-renderer\": \"17.0.2\",\r\n+    \"typescript\": \"^4.6.3\"\r\n+  },\r\n+  \"resolutions\": {\r\n+    \"@types/react\": \"^17\"\r\n+  },\r\n+  \"jest\": {\r\n+    \"preset\": \"react-native\",\r\n+    \"moduleFileExtensions\": [\r\n+      \"ts\",\r\n+      \"tsx\",\r\n+      \"js\",\r\n+      \"jsx\",\r\n+      \"json\",\r\n+      \"node\"\r\n+    ]\r\n+  }\r\n+}\r\n"
                }
            ],
            "date": 1651506984928,
            "name": "Commit-0",
            "content": "{\n  \"name\": \"app2\",\n  \"version\": \"0.0.1\",\n  \"private\": true,\n  \"scripts\": {\n    \"android\": \"react-native run-android\",\n    \"ios\": \"react-native run-ios\",\n    \"start\": \"react-native start\",\n    \"test\": \"jest\",\n    \"lint\": \"eslint . --ext .js,.jsx,.ts,.tsx\"\n  },\n  \"dependencies\": {\n    \"@react-navigation/bottom-tabs\": \"^6.3.1\",\n    \"@react-navigation/material-top-tabs\": \"^6.2.1\",\n    \"@react-navigation/native\": \"^6.0.10\",\n    \"@react-navigation/native-stack\": \"^6.6.1\",\n    \"react\": \"17.0.2\",\n    \"react-native\": \"0.68.0\",\n    \"react-native-pager-view\": \"^5.4.15\",\n    \"react-native-responsive-fontsize\": \"^0.5.1\",\n    \"react-native-safe-area-context\": \"^4.2.4\",\n    \"react-native-screens\": \"^3.13.1\",\n    \"react-native-tab-view\": \"^3.1.1\",\n    \"react-navigation-tabs\": \"^2.11.2\"\n  },\n  \"devDependencies\": {\n    \"@babel/core\": \"^7.12.9\",\n    \"@babel/runtime\": \"^7.12.5\",\n    \"@react-native-community/eslint-config\": \"^2.0.0\",\n    \"@types/jest\": \"^27.4.1\",\n    \"@types/react\": \"^18.0.3\",\n    \"@types/react-native\": \"^0.67.4\",\n    \"@types/react-test-renderer\": \"^18.0.0\",\n    \"@typescript-eslint/eslint-plugin\": \"^5.17.0\",\n    \"@typescript-eslint/parser\": \"^5.17.0\",\n    \"babel-jest\": \"^26.6.3\",\n    \"eslint\": \"^7.32.0\",\n    \"jest\": \"^26.6.3\",\n    \"metro-react-native-babel-preset\": \"^0.67.0\",\n    \"react-test-renderer\": \"17.0.2\",\n    \"typescript\": \"^4.6.3\"\n  },\n  \"resolutions\": {\n    \"@types/react\": \"^17\"\n  },\n  \"jest\": {\n    \"preset\": \"react-native\",\n    \"moduleFileExtensions\": [\n      \"ts\",\n      \"tsx\",\n      \"js\",\n      \"jsx\",\n      \"json\",\n      \"node\"\n    ]\n  }\n}\n"
        }
    ]
}